feastruct/__init__.py
feastruct/feastruct.py
feastruct-0.1.dist-info/METADATA
feastruct-0.1.dist-info/RECORD
feastruct-0.1.dist-info/WHEEL
feastruct-0.1.dist-info/top_level.txt
