Metadata-Version: 2.1
Name: feastruct
Version: 0.1
Summary: A python package for structural finite element analysis.
Home-page: https://github.com/robbievanleeuwen/feastruct
Author: Robbie van Leeuwen
Author-email: robbie.vanleeuwen@gmail.com
License: MIT
Platform: UNKNOWN
Requires-Dist: numpy
Requires-Dist: scipy
Requires-Dist: matplotlib
